{"name":"markmarkoh_kepler-confirmed-planets","title":"Kepler Confirmed Planets","description":"A dataset for the ~3,373 confirmed planets discovered by the Kepler Telescope\n\nKepler Telescope\n----\n\nUpdates!\nOver 100 **confirmed** exoplanets were found during Kepler's K2 mission.\n\n[Check out the new planets here](https://data.world/markmarkoh/kepler-confirmed-planets/query?query=%23+Kepler+planets+discovered+during+K2+mission%0A%0APREFIX+planets%3A+%3Chttp%3A%2F%2Fdata.world%2Fmarkmarkoh%2Fkepler-confirmed-planets%2Fplanets.csv%2Fplanets%23%3E%0APREFIX+rdf%3A+%3Chttp%3A%2F%2Fwww.w3.org%2F1999%2F02%2F22-rdf-syntax-ns%23%3E%0APREFIX+xsd%3A+%3Chttp%3A%2F%2Fwww.w3.org%2F2001%2FXMLSchema%23%3E%0A%0ASELECT+%3Frowupdate+%3Frowid+%3Fpl_hostname+%3Fpl_letter+%3Fpl_discmethod+%3Fpl_pnum+%3Fpl_orbper%0AWHERE+%7B%0A%3Fs+rdf%3Atype+%3Chttp%3A%2F%2Fdata.world%2Fmarkmarkoh%2Fkepler-confirmed-planets%2Fplanets.csv%2Fplanets%23%3E.%0A+%3Fs+planets%3Arowid+%3Frowid.++%0A+%3Fs+planets%3Apl_hostname+%3Fpl_hostname.++%0A+%3Fs+planets%3Apl_letter+%3Fpl_letter.+%0A+%3Fs+planets%3Apl_discmethod+%3Fpl_discmethod.%0A+%3Fs+planets%3Apl_pnum+%3Fpl_pnum.%0A+%3Fs+planets%3Apl_orbper+%3Fpl_orbper.%0A+%3Fs+planets%3Arowupdate+%3Frowupdate.%0A+FILTER+REGEX%28%3Fpl_hostname%2C+%22K2-%22%2C+%22i%22%29%0A%7D%0A), and read the [K2 Mission result announcement](https://uanews.arizona.edu/story/ualed-team-confirms-100plus-exoplanets-keplers-k2-mission).\n\nThe scientific objective of the Kepler Mission is to explore the structure and diversity of planetary systems. This is achieved by surveying a large sample of stars to:\n\n1. Determine the abundance of terrestrial and larger planets in or near the habitable zone of a wide variety of stars;\n2. Determine the distribution of sizes and shapes of the orbits of these planets;\n3. Estimate how many planets there are in multiple-star systems;\n4. Determine the variety of orbit sizes and planet reflectivities, sizes, masses and densities of short-period giant planets;\n5. Identify additional members of each discovered planetary system using other techniques; and\n6. Determine the properties of those stars that harbor planetary systems.\n\nThe Kepler Mission also supports the objectives of future NASA Origins theme missions Space Interferometry Mission (SIM) and Terrestrial Planet Finder (TPF),\n\n1. By identifying the common stellar characteristics of host stars for future planet searches,\n2. By defining the volume of space needed for the search and\n3. By allowing SIM to target systems already known to have terrestrial planets.\n\n([Source](http://kepler.nasa.gov/Mission/QuickGuide/)) \n\n\nHelpful links\n----\n\n[http://kepler.nasa.gov/Mission/QuickGuide/](http://kepler.nasa.gov/Mission/QuickGuide/)\n\n[http://exoplanetarchive.ipac.caltech.edu/index.html](http://exoplanetarchive.ipac.caltech.edu/index.html)\n\n[http://kepler.nasa.gov/](http://kepler.nasa.gov/)\n\n[http://www.nytimes.com/2015/07/24/science/space/kepler-data-reveals-what-might-be-best-goldilocks-planet-yet.html](http://www.nytimes.com/2015/07/24/science/space/kepler-data-reveals-what-might-be-best-goldilocks-planet-yet.html)\n\n\nSchema\n----\n\nThis file was produced by the NASA Exoplanet Archive  [http://exoplanetarchive.ipac.caltech.edu](http://exoplanetarchive.ipac.caltech.edu)\n\n    COLUMN pl_hostname:    Host Name\n    COLUMN pl_letter:      Planet Letter\n    COLUMN pl_discmethod:  Discovery Method\n    COLUMN pl_pnum:        Number of Planets in System\n    COLUMN pl_orbper:      Orbital Period [days]\n    COLUMN pl_orbpererr1:  Orbital Period Upper Unc. [days]\n    COLUMN pl_orbpererr2:  Orbital Period Lower Unc. [days]\n    COLUMN pl_orbperlim:   Orbital Period Limit Flag\n    COLUMN pl_orbsmax:     Orbit Semi-Major Axis [AU]\n    COLUMN pl_orbsmaxerr1: Orbit Semi-Major Axis Upper Unc. [AU]\n    COLUMN pl_orbsmaxerr2: Orbit Semi-Major Axis Lower Unc. [AU]\n    COLUMN pl_orbsmaxlim:  Orbit Semi-Major Axis Limit Flag\n    COLUMN pl_orbeccen:    Eccentricity\n    COLUMN pl_orbeccenerr1: Eccentricity Upper Unc.\n    COLUMN pl_orbeccenerr2: Eccentricity Lower Unc.\n    COLUMN pl_orbeccenlim: Eccentricity Limit Flag\n    COLUMN pl_orbincl:     Inclination [deg]\n    COLUMN pl_orbinclerr1: Inclination Upper Unc. [deg]\n    COLUMN pl_orbinclerr2: Inclination Lower Unc. [deg]\n    COLUMN pl_orbincllim:  Inclination Limit Flag\n    COLUMN pl_bmassj:      Planet Mass or M*sin(i)[Jupiter mass]\n    COLUMN pl_bmassjerr1:  Planet Mass or M*sin(i)Upper Unc. [Jupiter mass]\n    COLUMN pl_bmassjerr2:  Planet Mass or M*sin(i)Lower Unc. [Jupiter mass]\n    COLUMN pl_bmassjlim:   Planet Mass or M*sin(i)Limit Flag\n    COLUMN pl_bmassprov:   Planet Mass or M*sin(i) Provenance\n    COLUMN pl_radj:        Planet Radius [Jupiter radii]\n    COLUMN pl_radjerr1:    Planet Radius Upper Unc. [Jupiter radii]\n    COLUMN pl_radjerr2:    Planet Radius Lower Unc. [Jupiter radii]\n    COLUMN pl_radjlim:     Planet Radius Limit Flag\n    COLUMN pl_dens:        Planet Density [g/cm**3]\n    COLUMN pl_denserr1:    Planet Density Upper Unc. [g/cm**3]\n    COLUMN pl_denserr2:    Planet Density Lower Unc. [g/cm**3]\n    COLUMN pl_denslim:     Planet Density Limit Flag\n    COLUMN pl_ttvflag:     TTV Flag\n    COLUMN pl_kepflag:     Kepler Field Flag\n    COLUMN pl_k2flag:      K2 Mission Flag\n    COLUMN pl_nnotes:      Number of Notes\n    COLUMN ra_str:         RA [sexagesimal]\n    COLUMN ra:             RA [sexagesimal]\n    COLUMN dec_str:        Dec [sexagesimal]\n    COLUMN dec:            Dec [sexagesimal]\n    COLUMN st_dist:        Distance [pc]\n    COLUMN st_disterr1:    Distance Upper Unc. [pc]\n    COLUMN st_disterr2:    Distance Lower Unc. [pc]\n    COLUMN st_distlim:     Distance Limit Flag\n    COLUMN st_optmag:      Optical Magnitude [mag]\n    COLUMN st_optmagerr:   Optical Magnitude Unc. [mag]\n    COLUMN st_optmaglim:   Optical Magnitude Limit Flag\n    COLUMN st_optmagblend: Optical Magnitude Blend Flag\n    COLUMN st_optband:     Optical Magnitude Band\n    COLUMN st_teff:        Effective Temperature [K]\n    COLUMN st_tefferr1:    Effective Temperature Upper Unc. [K]\n    COLUMN st_tefferr2:    Effective Temperature Lower Unc. [K]\n    COLUMN st_tefflim:     Effective Temperature Limit Flag\n    COLUMN st_teffblend:   Effective Temperature Blend Flag\n    COLUMN st_mass:        Stellar Mass [Solar mass]\n    COLUMN st_masserr1:    Stellar Mass Upper Unc. [Solar mass]\n    COLUMN st_masserr2:    Stellar Mass Lower Unc. [Solar mass]\n    COLUMN st_masslim:     Stellar Mass Limit Flag\n    COLUMN st_massblend:   Stellar Mass Blend Flag\n    COLUMN st_rad:         Stellar Radius [Solar radii]\n    COLUMN st_raderr1:     Stellar Radius Upper Unc. [Solar radii]\n    COLUMN st_raderr2:     Stellar Radius Lower Unc. [Solar radii]\n    COLUMN st_radlim:      Stellar Radius Limit Flag\n    COLUMN st_radblend:    Stellar Radius Blend Flag\n    COLUMN rowupdate:      Date of Last Update","homepage":"https://data.world/markmarkoh/kepler-confirmed-planets","resources":[{"name":"planets","schema":{"fields":[{"name":"rowid","title":"rowid","type":"integer","rdfType":"http://www.w3.org/2001/XMLSchema#integer","dwSourceId":"rowid"},{"name":"pl_hostname","title":"pl_hostname","type":"string","rdfType":"http://www.w3.org/2001/XMLSchema#string","dwSourceId":"pl_hostname"},{"name":"pl_letter","title":"pl_letter","type":"string","rdfType":"http://www.w3.org/2001/XMLSchema#string","dwSourceId":"pl_letter"},{"name":"pl_discmethod","title":"pl_discmethod","type":"string","rdfType":"http://www.w3.org/2001/XMLSchema#string","dwSourceId":"pl_discmethod"},{"name":"pl_pnum","title":"pl_pnum","type":"integer","rdfType":"http://www.w3.org/2001/XMLSchema#integer","dwSourceId":"pl_pnum"},{"name":"pl_orbper","title":"pl_orbper","type":"number","rdfType":"http://www.w3.org/2001/XMLSchema#decimal","dwSourceId":"pl_orbper"},{"name":"pl_orbpererr1","title":"pl_orbpererr1","type":"number","rdfType":"http://www.w3.org/2001/XMLSchema#decimal","dwSourceId":"pl_orbpererr1"},{"name":"pl_orbpererr2","title":"pl_orbpererr2","type":"number","rdfType":"http://www.w3.org/2001/XMLSchema#decimal","dwSourceId":"pl_orbpererr2"},{"name":"pl_orbperlim","title":"pl_orbperlim","type":"integer","rdfType":"http://www.w3.org/2001/XMLSchema#integer","dwSourceId":"pl_orbperlim"},{"name":"pl_orbsmax","title":"pl_orbsmax","type":"number","rdfType":"http://www.w3.org/2001/XMLSchema#decimal","dwSourceId":"pl_orbsmax"},{"name":"pl_orbsmaxerr1","title":"pl_orbsmaxerr1","type":"number","rdfType":"http://www.w3.org/2001/XMLSchema#decimal","dwSourceId":"pl_orbsmaxerr1"},{"name":"pl_orbsmaxerr2","title":"pl_orbsmaxerr2","type":"number","rdfType":"http://www.w3.org/2001/XMLSchema#decimal","dwSourceId":"pl_orbsmaxerr2"},{"name":"pl_orbsmaxlim","title":"pl_orbsmaxlim","type":"boolean","rdfType":"http://www.w3.org/2001/XMLSchema#boolean","dwSourceId":"pl_orbsmaxlim"},{"name":"pl_orbeccen","title":"pl_orbeccen","type":"number","rdfType":"http://www.w3.org/2001/XMLSchema#decimal","dwSourceId":"pl_orbeccen"},{"name":"pl_orbeccenerr1","title":"pl_orbeccenerr1","type":"number","rdfType":"http://www.w3.org/2001/XMLSchema#decimal","dwSourceId":"pl_orbeccenerr1"},{"name":"pl_orbeccenerr2","title":"pl_orbeccenerr2","type":"number","rdfType":"http://www.w3.org/2001/XMLSchema#decimal","dwSourceId":"pl_orbeccenerr2"},{"name":"pl_orbeccenlim","title":"pl_orbeccenlim","type":"integer","rdfType":"http://www.w3.org/2001/XMLSchema#integer","dwSourceId":"pl_orbeccenlim"},{"name":"pl_orbincl","title":"pl_orbincl","type":"number","rdfType":"http://www.w3.org/2001/XMLSchema#decimal","dwSourceId":"pl_orbincl"},{"name":"pl_orbinclerr1","title":"pl_orbinclerr1","type":"number","rdfType":"http://www.w3.org/2001/XMLSchema#decimal","dwSourceId":"pl_orbinclerr1"},{"name":"pl_orbinclerr2","title":"pl_orbinclerr2","type":"number","rdfType":"http://www.w3.org/2001/XMLSchema#decimal","dwSourceId":"pl_orbinclerr2"},{"name":"pl_orbincllim","title":"pl_orbincllim","type":"integer","rdfType":"http://www.w3.org/2001/XMLSchema#integer","dwSourceId":"pl_orbincllim"},{"name":"pl_bmassj","title":"pl_bmassj","type":"number","rdfType":"http://www.w3.org/2001/XMLSchema#decimal","dwSourceId":"pl_bmassj"},{"name":"pl_bmassjerr1","title":"pl_bmassjerr1","type":"number","rdfType":"http://www.w3.org/2001/XMLSchema#decimal","dwSourceId":"pl_bmassjerr1"},{"name":"pl_bmassjerr2","title":"pl_bmassjerr2","type":"number","rdfType":"http://www.w3.org/2001/XMLSchema#decimal","dwSourceId":"pl_bmassjerr2"},{"name":"pl_bmassjlim","title":"pl_bmassjlim","type":"integer","rdfType":"http://www.w3.org/2001/XMLSchema#integer","dwSourceId":"pl_bmassjlim"},{"name":"pl_bmassprov","title":"pl_bmassprov","type":"string","rdfType":"http://www.w3.org/2001/XMLSchema#string","dwSourceId":"pl_bmassprov"},{"name":"pl_radj","title":"pl_radj","type":"number","rdfType":"http://www.w3.org/2001/XMLSchema#decimal","dwSourceId":"pl_radj"},{"name":"pl_radjerr1","title":"pl_radjerr1","type":"number","rdfType":"http://www.w3.org/2001/XMLSchema#decimal","dwSourceId":"pl_radjerr1"},{"name":"pl_radjerr2","title":"pl_radjerr2","type":"number","rdfType":"http://www.w3.org/2001/XMLSchema#decimal","dwSourceId":"pl_radjerr2"},{"name":"pl_radjlim","title":"pl_radjlim","type":"boolean","rdfType":"http://www.w3.org/2001/XMLSchema#boolean","dwSourceId":"pl_radjlim"},{"name":"pl_dens","title":"pl_dens","type":"number","rdfType":"http://www.w3.org/2001/XMLSchema#decimal","dwSourceId":"pl_dens"},{"name":"pl_denserr1","title":"pl_denserr1","type":"number","rdfType":"http://www.w3.org/2001/XMLSchema#decimal","dwSourceId":"pl_denserr1"},{"name":"pl_denserr2","title":"pl_denserr2","type":"number","rdfType":"http://www.w3.org/2001/XMLSchema#decimal","dwSourceId":"pl_denserr2"},{"name":"pl_denslim","title":"pl_denslim","type":"integer","rdfType":"http://www.w3.org/2001/XMLSchema#integer","dwSourceId":"pl_denslim"},{"name":"pl_ttvflag","title":"pl_ttvflag","type":"boolean","rdfType":"http://www.w3.org/2001/XMLSchema#boolean","dwSourceId":"pl_ttvflag"},{"name":"pl_kepflag","title":"pl_kepflag","type":"boolean","rdfType":"http://www.w3.org/2001/XMLSchema#boolean","dwSourceId":"pl_kepflag"},{"name":"pl_k2flag","title":"pl_k2flag","type":"boolean","rdfType":"http://www.w3.org/2001/XMLSchema#boolean","dwSourceId":"pl_k2flag"},{"name":"pl_nnotes","title":"pl_nnotes","type":"integer","rdfType":"http://www.w3.org/2001/XMLSchema#integer","dwSourceId":"pl_nnotes"},{"name":"ra_str","title":"ra_str","type":"string","rdfType":"http://www.w3.org/2001/XMLSchema#string","dwSourceId":"ra_str"},{"name":"ra","title":"ra","type":"number","rdfType":"http://www.w3.org/2001/XMLSchema#decimal","dwSourceId":"ra"},{"name":"dec_str","title":"dec_str","type":"string","rdfType":"http://www.w3.org/2001/XMLSchema#string","dwSourceId":"dec_str"},{"name":"dec","title":"dec","type":"number","rdfType":"http://www.w3.org/2001/XMLSchema#decimal","dwSourceId":"dec"},{"name":"st_dist","title":"st_dist","type":"number","rdfType":"http://www.w3.org/2001/XMLSchema#decimal","dwSourceId":"st_dist"},{"name":"st_disterr1","title":"st_disterr1","type":"number","rdfType":"http://www.w3.org/2001/XMLSchema#decimal","dwSourceId":"st_disterr1"},{"name":"st_disterr2","title":"st_disterr2","type":"number","rdfType":"http://www.w3.org/2001/XMLSchema#decimal","dwSourceId":"st_disterr2"},{"name":"st_distlim","title":"st_distlim","type":"integer","rdfType":"http://www.w3.org/2001/XMLSchema#integer","dwSourceId":"st_distlim"},{"name":"st_optmag","title":"st_optmag","type":"number","rdfType":"http://www.w3.org/2001/XMLSchema#decimal","dwSourceId":"st_optmag"},{"name":"st_optmagerr","title":"st_optmagerr","type":"number","rdfType":"http://www.w3.org/2001/XMLSchema#decimal","dwSourceId":"st_optmagerr"},{"name":"st_optmaglim","title":"st_optmaglim","type":"boolean","rdfType":"http://www.w3.org/2001/XMLSchema#boolean","dwSourceId":"st_optmaglim"},{"name":"st_optmagblend","title":"st_optmagblend","type":"boolean","rdfType":"http://www.w3.org/2001/XMLSchema#boolean","dwSourceId":"st_optmagblend"},{"name":"st_optband","title":"st_optband","type":"string","rdfType":"http://www.w3.org/2001/XMLSchema#string","dwSourceId":"st_optband"},{"name":"st_teff","title":"st_teff","type":"number","rdfType":"http://www.w3.org/2001/XMLSchema#decimal","dwSourceId":"st_teff"},{"name":"st_tefferr1","title":"st_tefferr1","type":"number","rdfType":"http://www.w3.org/2001/XMLSchema#decimal","dwSourceId":"st_tefferr1"},{"name":"st_tefferr2","title":"st_tefferr2","type":"number","rdfType":"http://www.w3.org/2001/XMLSchema#decimal","dwSourceId":"st_tefferr2"},{"name":"st_tefflim","title":"st_tefflim","type":"boolean","rdfType":"http://www.w3.org/2001/XMLSchema#boolean","dwSourceId":"st_tefflim"},{"name":"st_teffblend","title":"st_teffblend","type":"boolean","rdfType":"http://www.w3.org/2001/XMLSchema#boolean","dwSourceId":"st_teffblend"},{"name":"st_mass","title":"st_mass","type":"number","rdfType":"http://www.w3.org/2001/XMLSchema#decimal","dwSourceId":"st_mass"},{"name":"st_masserr1","title":"st_masserr1","type":"number","rdfType":"http://www.w3.org/2001/XMLSchema#decimal","dwSourceId":"st_masserr1"},{"name":"st_masserr2","title":"st_masserr2","type":"number","rdfType":"http://www.w3.org/2001/XMLSchema#decimal","dwSourceId":"st_masserr2"},{"name":"st_masslim","title":"st_masslim","type":"integer","rdfType":"http://www.w3.org/2001/XMLSchema#integer","dwSourceId":"st_masslim"},{"name":"st_massblend","title":"st_massblend","type":"boolean","rdfType":"http://www.w3.org/2001/XMLSchema#boolean","dwSourceId":"st_massblend"},{"name":"st_rad","title":"st_rad","type":"number","rdfType":"http://www.w3.org/2001/XMLSchema#decimal","dwSourceId":"st_rad"},{"name":"st_raderr1","title":"st_raderr1","type":"number","rdfType":"http://www.w3.org/2001/XMLSchema#decimal","dwSourceId":"st_raderr1"},{"name":"st_raderr2","title":"st_raderr2","type":"number","rdfType":"http://www.w3.org/2001/XMLSchema#decimal","dwSourceId":"st_raderr2"},{"name":"st_radlim","title":"st_radlim","type":"boolean","rdfType":"http://www.w3.org/2001/XMLSchema#boolean","dwSourceId":"st_radlim"},{"name":"st_radblend","title":"st_radblend","type":"boolean","rdfType":"http://www.w3.org/2001/XMLSchema#boolean","dwSourceId":"st_radblend"},{"name":"rowupdate","title":"rowupdate","type":"date","rdfType":"http://www.w3.org/2001/XMLSchema#date","dwSourceId":"rowupdate"}]},"path":"data/planets.csv","format":"csv"},{"name":"original/planets.csv","path":"original/planets.csv","format":"csv","mediatype":"text/csv","bytes":1007347}],"keywords":["space","kepler","planet","kepler telescope","astronomy","contributors wanted"]}